trulens/providers/cortex/__init__.py
trulens/providers/cortex/config/cortex_model_costs.json
trulens/providers/cortex/endpoint.py
trulens/providers/cortex/provider.py
trulens/providers/cortex/py.typed
trulens_providers_cortex-2.5.3.dist-info/METADATA
trulens_providers_cortex-2.5.3.dist-info/WHEEL
trulens_providers_cortex-2.5.3.dist-info/RECORD
