Metadata-Version: 2.1
Name: trulens-providers-cortex
Version: 2.5.3
Summary: A TruLens extension package adding Snowflake Cortex support for LLM App evaluation.
Home-page: https://trulens.org/
License: MIT
Author: Snowflake Inc.
Author-email: ml-observability-wg-dl@snowflake.com
Requires-Python: >=3.9,<3.13
Classifier: Development Status :: 3 - Alpha
Classifier: License :: OSI Approved :: MIT License
Classifier: Operating System :: OS Independent
Classifier: Programming Language :: Python :: 3
Classifier: Programming Language :: Python :: 3.9
Classifier: Programming Language :: Python :: 3.10
Classifier: Programming Language :: Python :: 3.11
Classifier: Programming Language :: Python :: 3.12
Requires-Dist: packaging (>=23.0)
Requires-Dist: snowflake-connector-python (>=3.15,<4.0)
Requires-Dist: snowflake-ml-python (>=1.7.2,<2.0.0)
Requires-Dist: snowflake-snowpark-python (>=1.18.0,<2.0.0)
Requires-Dist: trulens-core (>=2.0.0,<3.0.0)
Requires-Dist: trulens-feedback (>=2.0.0,<3.0.0)
Project-URL: Documentation, https://trulens.org/getting_started/
Project-URL: Repository, https://github.com/truera/trulens
